materialdatabase/__init__.py
materialdatabase/constants.py
materialdatabase/dtos.py
materialdatabase/enumerations.py
materialdatabase/material_data_base_classes.py
materialdatabase/material_data_base_functions.py
materialdatabase/paths_example.py
materialdatabase/trial_database.py
materialdatabase/utils.py
materialdatabase/data/material_data_base.json
materialdatabase/helper_functions/get_permeability_data_from_LEA_LK.py
materialdatabase/helper_functions/get_property_from_LEA_LK.py
materialdatabase/notebooks/compare_material.ipynb
materialdatabase/notebooks/steinmetz_N95_example.ipynb
materialdatabase/notebooks/steinmetz_fit.ipynb
materialdatabase/scripts/write_LEA_LK_permeability_data_into_database.py
materialdatabase/scripts/write_LEA_LK_permittivity_data_into_database.py
materialdatabase/scripts/write_LEA_MTB_data_into_database.py
materialdatabase/scripts/write_MagNet_permeability_into_database.py
materialdatabase/scripts/write_datasheet_permeability_data_into_database.py
materialdatabase/scripts/write_wayne_kerr_permeability_data_into_database.py
materialdatabase/scripts/write_wayne_kerr_permittivity_data_into_database.py
materialdatabase-0.3.0.data/data/CHANGELOG.md
materialdatabase-0.3.0.dist-info/LICENSE
materialdatabase-0.3.0.dist-info/METADATA
materialdatabase-0.3.0.dist-info/WHEEL
materialdatabase-0.3.0.dist-info/top_level.txt
materialdatabase-0.3.0.dist-info/RECORD
