Metadata-Version: 2.1
Name: materialdatabase
Version: 0.3.0
Summary: materialdatabase
Home-page: https://github.com/upb-lea/materialdatabase
Author: LEA - Uni Paderborn
Author-email: upblea@mail.upb.de
License: GNU General Public License v3
Project-URL: Documentation, https://upb-lea.github.io/materialdatabase/
Project-URL: Source Code, https://github.com/upb-lea/materialdatabase
Keywords: materialdatabase
Classifier: Development Status :: 3 - Alpha
Classifier: Intended Audience :: Developers
Classifier: License :: OSI Approved :: GNU General Public License v3 (GPLv3)
Classifier: Natural Language :: English
Classifier: Topic :: Scientific/Engineering
Classifier: Programming Language :: Python :: 3
Classifier: Programming Language :: Python :: 3.10
Classifier: Programming Language :: Python :: 3.11
Classifier: Programming Language :: Python :: 3.12
Classifier: Operating System :: Microsoft :: Windows
Classifier: Operating System :: POSIX :: Linux
Classifier: Environment :: MacOS X
Requires-Python: >=3.10
License-File: LICENSE
Requires-Dist: numpy ~=1.26.0
Requires-Dist: scipy >=1.6.0
Requires-Dist: setuptools >=49.2.1
Requires-Dist: matplotlib >=3.3.4
Requires-Dist: pytest >=6.2.4
Requires-Dist: mplcursors
Requires-Dist: deepdiff
